{
  "basic_info": {
    "name": "Hello! I'm Arunabh Roy",
    "titles": [
      "Web Developer",
      "UI/UX Designer",
      "Frontend Developer",
      "DevOps and Security Enthusiast",
      "E-Commerce Integration",
      "Masters in Information Systems"
    ],
    "social": [
      {
        "name": "github",
        "url": "https://github.com/abho11",
        "class": "fab fa-github"
      },
      {
        "name": "linkedin",
        "url": "https://www.linkedin.com/in/arunabh-roy/",
        "class": "fab fa-linkedin"
      },
      {
        "name": "email",
        "url": "mailto:royarunabh121@gmail.com",
        "class": "fas fa-envelope"
      },
      {
        "name": "phone",
        "url": "tel:6506649524",
        "class": "fas fa-phone"
      }
    ],
    "image": "myProfile.jpeg"
  },
  "skills": {
    "icons": [
      {
        "name": "ReactJS",
        "class": "devicon-react-original",
        "level": "90"
      },
      {
        "name": "NodeJS",
        "class": "devicon-nodejs-plain",
        "level": "85"
      },
      {
        "name": "Angular",
        "class": "devicon-angularjs-plain",
        "level": "80"
      },
      {
        "name": "Python",
        "class": "devicon-python-plain",
        "level": "85"
      },
      {
        "name": "SQL/NoSQL",
        "class": "devicon-mongodb-plain",
        "level": "95"
      },
      {
        "name": "AWS",
        "class": "devicon-amazonwebservices-plain",
        "level": "80"
      },
      {
        "name": "JavaScript",
        "class": "devicon-javascript-plain",
        "level": "90"
      },
      {
        "name": "HTML5",
        "class": "devicon-html5-plain",
        "level": "95"
      },
      {
        "name": "CSS3",
        "class": "devicon-css3-plain",
        "level": "95"
      },
      {
        "name": "Sass",
        "class": "devicon-sass-plain",
        "level": "90"
      }
    ]
  }
}